eyefocus/__init__.py
eyefocus/icon.png
eyefocus/sound.wav
eyefocus/utils.py
eyefocus-0.3.0.dist-info/METADATA
eyefocus-0.3.0.dist-info/WHEEL
eyefocus-0.3.0.dist-info/entry_points.txt
eyefocus-0.3.0.dist-info/licenses/LICENSE
eyefocus-0.3.0.dist-info/RECORD
