Metadata-Version: 2.3
Name: eyefocus
Version: 0.3.0
Summary: Stay focused!
License-File: LICENSE
Requires-Python: >=3.12
Requires-Dist: huggingface-hub[hf-transfer]>=0.24.7
Requires-Dist: llama-cpp-python==0.2.90
Requires-Dist: mss>=9.0.2
Requires-Dist: notify-py>=0.3.43
Requires-Dist: pre-commit>=3.8.0
Requires-Dist: timm>=1.0.9
Requires-Dist: typer>=0.12.5
Provides-Extra: fe
Requires-Dist: modal>=0.64.145; extra == 'fe'
Provides-Extra: ft
Requires-Dist: accelerate>=0.34.2; extra == 'ft'
Requires-Dist: bitsandbytes>=0.44.0; extra == 'ft'
Requires-Dist: datasets>=3.0.0; extra == 'ft'
Requires-Dist: modal>=0.64.128; extra == 'ft'
Requires-Dist: python-dotenv>=1.0.1; extra == 'ft'
Requires-Dist: sentencepiece>=0.2.0; extra == 'ft'
Requires-Dist: term-image>=0.7.2; extra == 'ft'
Requires-Dist: transformers>=4.45.1; extra == 'ft'
Requires-Dist: wandb>=0.18.1; extra == 'ft'
Provides-Extra: gpu
Requires-Dist: flash-attn>=2.6.3; extra == 'gpu'
